capitalg/CostBaseQueue.py
capitalg/TransactionLoader.py
capitalg/Writer.py
capitalg/__init__.py
capitalg/cg_helpers.py
capitalg/commands.py
capitalg/contstants.py
capitalg/errors.py
capitalg/main.py
capitalg/rates_loader.py
capitalg/utils.py
capitalg/analysis/__init__.py
capitalg/analysis/balance.py
capitalg/analysis/summary.py
capitalg-0.0.1.dist-info/LICENSE
capitalg-0.0.1.dist-info/METADATA
capitalg-0.0.1.dist-info/WHEEL
capitalg-0.0.1.dist-info/entry_points.txt
capitalg-0.0.1.dist-info/top_level.txt
capitalg-0.0.1.dist-info/RECORD
