Metadata-Version: 2.1
Name: capitalg
Version: 0.0.1
Summary: Capital Gains Calculator
Home-page: https://github.com/dleber/capitalg
Author: dleber
Author-email: 
License: GNU
Project-URL: Bug Tracker, https://github.com/dleber/capitalg/issues
Keywords: capitalg,capital gains,capital gains tax calculator,crypto tax
Platform: UNKNOWN
Classifier: Programming Language :: Python :: 3
Classifier: License :: OSI Approved :: GNU General Public License v3 (GPLv3)
Classifier: Operating System :: OS Independent
Requires-Python: >=3.6
License-File: LICENSE
Requires-Dist: pytz (>=2020.1)
